food_tracker.py
mseep_food_tracker-0.1.1.dist-info/METADATA
mseep_food_tracker-0.1.1.dist-info/WHEEL
mseep_food_tracker-0.1.1.dist-info/entry_points.txt
mseep_food_tracker-0.1.1.dist-info/top_level.txt
mseep_food_tracker-0.1.1.dist-info/RECORD
